htLib/__init__.py
htLib/bserial.py
htLib/mail.py
htLib/ubidots.py
htlib-0.14.dist-info/License.txt
htlib-0.14.dist-info/METADATA
htlib-0.14.dist-info/WHEEL
htlib-0.14.dist-info/top_level.txt
htlib-0.14.dist-info/RECORD
