Metadata-Version: 2.1
Name: htlib
Version: 0.14
Summary: htlib package
Home-page: https://github.com/harol1997/htlib
Author: Harol Alvarado, Hedrich Apaza
Author-email: harolav3@gmail.com, Vlandemir2411@hotmail.com
License: UNKNOWN
Platform: UNKNOWN
Classifier: Programming Language :: Python :: 3
Classifier: License :: OSI Approved :: MIT License
Requires-Python: >=3.6
License-File: License.txt
Requires-Dist: pyserial (==3.5)
Requires-Dist: requests (==2.26.0)
